{"config":{"chunk_size":1000,"engine_timings":true,"guid_policy":"fail_fast","heartbeat_s":10,"iterations":1,"metrics":["diff_graphs"],"profile":"semantic_stable","warmup":0},"environment":{"ifcopenshell":{"version":"0.8.4.post1"},"platform":{"machine":"arm64","release":"25.3.0","system":"Darwin"},"python":{"implementation":"CPython","version":"3.12.0","version_info":{"major":3,"micro":0,"minor":12}}},"generated_at":"2026-03-13T02:45:29.113412+00:00","results":[{"case":{"name":"house_v1_v2_scrambled","new_path":"/Users/imantsliepins/Personal/Athar/tests/fixtures/house_v2_scrambled.ifc","old_path":"/Users/imantsliepins/Personal/Athar/tests/fixtures/house_v1.ifc"},"metrics":{"diff_graphs":{"engine_timings_ms":{"samples":{"context.apply_equivalence_classes":[0.058],"context.apply_path_matches":[3.831],"context.apply_secondary_matches":[0.045],"context.apply_text_fingerprint_matches":[721.898],"context.assign_new_ids":[3442.223],"context.assign_new_ids.wl_rounds":[3.0],"context.assign_new_ids.wl_total_ms":[3583.9],"context.assign_old_ids":[7142.073],"context.assign_old_ids.wl_rounds":[3.0],"context.assign_old_ids.wl_total_ms":[3590.351],"context.build_compare_entities":[0.004],"context.build_owner_projectors":[514.247],"context.build_stats":[3839.74],"context.index_new_by_identity":[4732.347],"context.index_old_by_identity":[8152.794],"context.match_after_path":[2531.144],"context.match_root_steps":[18.212],"context.match_unique_ids":[2889.005],"context.path_propagation":[111.474],"context.path_propagation.reused_early":[0.0],"context.precompute_new_identity":[61567.509],"context.precompute_old_identity":[56606.284],"context.root_remap":[23139.807],"context.secondary_match":[1805.131],"context.seed_guid_pairs":[1132.902],"context.seed_guid_pairs.coverage":[0.0],"context.seed_guid_pairs.matched":[0.0],"context.seed_guid_pairs.unique_guid_overlap":[0.0],"context.seed_guid_path_propagation":[0.003],"context.seed_text_fingerprints":[40020.913],"context.seed_text_fingerprints.ambiguous_buckets":[30551.0],"context.seed_text_fingerprints.matched":[114512.0],"context.seed_text_fingerprints.parallel":[0.0],"emit_base_changes":[10736.743],"emit_derived_markers":[6761.257],"prepare_context":[289665.985],"total":[307194.688]},"summary":{"context.apply_equivalence_classes":{"max":0.058,"mean":0.058,"median":0.058,"min":0.058,"p95":0.058},"context.apply_path_matches":{"max":3.831,"mean":3.831,"median":3.831,"min":3.831,"p95":3.831},"context.apply_secondary_matches":{"max":0.045,"mean":0.045,"median":0.045,"min":0.045,"p95":0.045},"context.apply_text_fingerprint_matches":{"max":721.898,"mean":721.898,"median":721.898,"min":721.898,"p95":721.898},"context.assign_new_ids":{"max":3442.223,"mean":3442.223,"median":3442.223,"min":3442.223,"p95":3442.223},"context.assign_new_ids.wl_rounds":{"max":3.0,"mean":3.0,"median":3.0,"min":3.0,"p95":3.0},"context.assign_new_ids.wl_total_ms":{"max":3583.9,"mean":3583.9,"median":3583.9,"min":3583.9,"p95":3583.9},"context.assign_old_ids":{"max":7142.073,"mean":7142.073,"median":7142.073,"min":7142.073,"p95":7142.073},"context.assign_old_ids.wl_rounds":{"max":3.0,"mean":3.0,"median":3.0,"min":3.0,"p95":3.0},"context.assign_old_ids.wl_total_ms":{"max":3590.351,"mean":3590.351,"median":3590.351,"min":3590.351,"p95":3590.351},"context.build_compare_entities":{"max":0.004,"mean":0.004,"median":0.004,"min":0.004,"p95":0.004},"context.build_owner_projectors":{"max":514.247,"mean":514.247,"median":514.247,"min":514.247,"p95":514.247},"context.build_stats":{"max":3839.74,"mean":3839.74,"median":3839.74,"min":3839.74,"p95":3839.74},"context.index_new_by_identity":{"max":4732.347,"mean":4732.347,"median":4732.347,"min":4732.347,"p95":4732.347},"context.index_old_by_identity":{"max":8152.794,"mean":8152.794,"median":8152.794,"min":8152.794,"p95":8152.794},"context.match_after_path":{"max":2531.144,"mean":2531.144,"median":2531.144,"min":2531.144,"p95":2531.144},"context.match_root_steps":{"max":18.212,"mean":18.212,"median":18.212,"min":18.212,"p95":18.212},"context.match_unique_ids":{"max":2889.005,"mean":2889.005,"median":2889.005,"min":2889.005,"p95":2889.005},"context.path_propagation":{"max":111.474,"mean":111.474,"median":111.474,"min":111.474,"p95":111.474},"context.path_propagation.reused_early":{"max":0.0,"mean":0.0,"median":0.0,"min":0.0,"p95":0.0},"context.precompute_new_identity":{"max":61567.509,"mean":61567.509,"median":61567.509,"min":61567.509,"p95":61567.509},"context.precompute_old_identity":{"max":56606.284,"mean":56606.284,"median":56606.284,"min":56606.284,"p95":56606.284},"context.root_remap":{"max":23139.807,"mean":23139.807,"median":23139.807,"min":23139.807,"p95":23139.807},"context.secondary_match":{"max":1805.131,"mean":1805.131,"median":1805.131,"min":1805.131,"p95":1805.131},"context.seed_guid_pairs":{"max":1132.902,"mean":1132.902,"median":1132.902,"min":1132.902,"p95":1132.902},"context.seed_guid_pairs.coverage":{"max":0.0,"mean":0.0,"median":0.0,"min":0.0,"p95":0.0},"context.seed_guid_pairs.matched":{"max":0.0,"mean":0.0,"median":0.0,"min":0.0,"p95":0.0},"context.seed_guid_pairs.unique_guid_overlap":{"max":0.0,"mean":0.0,"median":0.0,"min":0.0,"p95":0.0},"context.seed_guid_path_propagation":{"max":0.003,"mean":0.003,"median":0.003,"min":0.003,"p95":0.003},"context.seed_text_fingerprints":{"max":40020.913,"mean":40020.913,"median":40020.913,"min":40020.913,"p95":40020.913},"context.seed_text_fingerprints.ambiguous_buckets":{"max":30551.0,"mean":30551.0,"median":30551.0,"min":30551.0,"p95":30551.0},"context.seed_text_fingerprints.matched":{"max":114512.0,"mean":114512.0,"median":114512.0,"min":114512.0,"p95":114512.0},"context.seed_text_fingerprints.parallel":{"max":0.0,"mean":0.0,"median":0.0,"min":0.0,"p95":0.0},"emit_base_changes":{"max":10736.743,"mean":10736.743,"median":10736.743,"min":10736.743,"p95":10736.743},"emit_derived_markers":{"max":6761.257,"mean":6761.257,"median":6761.257,"min":6761.257,"p95":6761.257},"prepare_context":{"max":289665.985,"mean":289665.985,"median":289665.985,"min":289665.985,"p95":289665.985},"total":{"max":307194.688,"mean":307194.688,"median":307194.688,"min":307194.688,"p95":307194.688}}},"output_signature":{"base_change_count":6240,"derived_marker_count":0},"samples":{"peak_mem_bytes":[6678591558],"time_ms":[320175.205]},"stable_output_signature":true,"summary":{"peak_mem_bytes":{"max":6678591558,"mean":6678591558,"median":6678591558,"min":6678591558,"p95":6678591558},"time_ms":{"max":320175.205,"mean":320175.205,"median":320175.205,"min":320175.205,"p95":320175.205}}}},"parse_ms":{"new_graph":46136.76,"old_graph":38470.673,"total":84607.433}},{"case":{"name":"basichouse_v1_v2","new_path":"/Users/imantsliepins/Personal/Athar/tests/fixtures/BasicHouse_modified.ifc","old_path":"/Users/imantsliepins/Personal/Athar/tests/fixtures/BasicHouse.ifc"},"metrics":{"diff_graphs":{"engine_timings_ms":{"samples":{"context.apply_equivalence_classes":[1.147],"context.apply_path_matches":[17.644],"context.apply_secondary_matches":[0.14],"context.apply_text_fingerprint_matches":[716.228],"context.assign_new_ids":[5604.254],"context.assign_new_ids.wl_rounds":[3.0],"context.assign_new_ids.wl_total_ms":[3365.322],"context.assign_old_ids":[3956.308],"context.assign_old_ids.wl_rounds":[3.0],"context.assign_old_ids.wl_total_ms":[3655.382],"context.build_compare_entities":[0.005],"context.build_owner_projectors":[495.875],"context.build_stats":[3846.963],"context.index_new_by_identity":[4938.997],"context.index_old_by_identity":[7810.581],"context.match_after_path":[2917.925],"context.match_root_steps":[21.735],"context.match_unique_ids":[2973.154],"context.path_propagation":[266.744],"context.path_propagation.reused_early":[0.0],"context.precompute_new_identity":[55922.366],"context.precompute_old_identity":[53837.767],"context.root_remap":[4474.654],"context.secondary_match":[2160.836],"context.seed_guid_pairs":[1439.585],"context.seed_guid_pairs.coverage":[0.003],"context.seed_guid_pairs.matched":[3407.0],"context.seed_guid_pairs.unique_guid_overlap":[0.999],"context.seed_guid_path_propagation":[0.007],"context.seed_text_fingerprints":[40948.54],"context.seed_text_fingerprints.ambiguous_buckets":[30548.0],"context.seed_text_fingerprints.matched":[114515.0],"context.seed_text_fingerprints.parallel":[0.0],"emit_base_changes":[10110.636],"emit_derived_markers":[8777.32],"prepare_context":[265847.346],"total":[295944.008]},"summary":{"context.apply_equivalence_classes":{"max":1.147,"mean":1.147,"median":1.147,"min":1.147,"p95":1.147},"context.apply_path_matches":{"max":17.644,"mean":17.644,"median":17.644,"min":17.644,"p95":17.644},"context.apply_secondary_matches":{"max":0.14,"mean":0.14,"median":0.14,"min":0.14,"p95":0.14},"context.apply_text_fingerprint_matches":{"max":716.228,"mean":716.228,"median":716.228,"min":716.228,"p95":716.228},"context.assign_new_ids":{"max":5604.254,"mean":5604.254,"median":5604.254,"min":5604.254,"p95":5604.254},"context.assign_new_ids.wl_rounds":{"max":3.0,"mean":3.0,"median":3.0,"min":3.0,"p95":3.0},"context.assign_new_ids.wl_total_ms":{"max":3365.322,"mean":3365.322,"median":3365.322,"min":3365.322,"p95":3365.322},"context.assign_old_ids":{"max":3956.308,"mean":3956.308,"median":3956.308,"min":3956.308,"p95":3956.308},"context.assign_old_ids.wl_rounds":{"max":3.0,"mean":3.0,"median":3.0,"min":3.0,"p95":3.0},"context.assign_old_ids.wl_total_ms":{"max":3655.382,"mean":3655.382,"median":3655.382,"min":3655.382,"p95":3655.382},"context.build_compare_entities":{"max":0.005,"mean":0.005,"median":0.005,"min":0.005,"p95":0.005},"context.build_owner_projectors":{"max":495.875,"mean":495.875,"median":495.875,"min":495.875,"p95":495.875},"context.build_stats":{"max":3846.963,"mean":3846.963,"median":3846.963,"min":3846.963,"p95":3846.963},"context.index_new_by_identity":{"max":4938.997,"mean":4938.997,"median":4938.997,"min":4938.997,"p95":4938.997},"context.index_old_by_identity":{"max":7810.581,"mean":7810.581,"median":7810.581,"min":7810.581,"p95":7810.581},"context.match_after_path":{"max":2917.925,"mean":2917.925,"median":2917.925,"min":2917.925,"p95":2917.925},"context.match_root_steps":{"max":21.735,"mean":21.735,"median":21.735,"min":21.735,"p95":21.735},"context.match_unique_ids":{"max":2973.154,"mean":2973.154,"median":2973.154,"min":2973.154,"p95":2973.154},"context.path_propagation":{"max":266.744,"mean":266.744,"median":266.744,"min":266.744,"p95":266.744},"context.path_propagation.reused_early":{"max":0.0,"mean":0.0,"median":0.0,"min":0.0,"p95":0.0},"context.precompute_new_identity":{"max":55922.366,"mean":55922.366,"median":55922.366,"min":55922.366,"p95":55922.366},"context.precompute_old_identity":{"max":53837.767,"mean":53837.767,"median":53837.767,"min":53837.767,"p95":53837.767},"context.root_remap":{"max":4474.654,"mean":4474.654,"median":4474.654,"min":4474.654,"p95":4474.654},"context.secondary_match":{"max":2160.836,"mean":2160.836,"median":2160.836,"min":2160.836,"p95":2160.836},"context.seed_guid_pairs":{"max":1439.585,"mean":1439.585,"median":1439.585,"min":1439.585,"p95":1439.585},"context.seed_guid_pairs.coverage":{"max":0.003,"mean":0.003,"median":0.003,"min":0.003,"p95":0.003},"context.seed_guid_pairs.matched":{"max":3407.0,"mean":3407.0,"median":3407.0,"min":3407.0,"p95":3407.0},"context.seed_guid_pairs.unique_guid_overlap":{"max":0.999,"mean":0.999,"median":0.999,"min":0.999,"p95":0.999},"context.seed_guid_path_propagation":{"max":0.007,"mean":0.007,"median":0.007,"min":0.007,"p95":0.007},"context.seed_text_fingerprints":{"max":40948.54,"mean":40948.54,"median":40948.54,"min":40948.54,"p95":40948.54},"context.seed_text_fingerprints.ambiguous_buckets":{"max":30548.0,"mean":30548.0,"median":30548.0,"min":30548.0,"p95":30548.0},"context.seed_text_fingerprints.matched":{"max":114515.0,"mean":114515.0,"median":114515.0,"min":114515.0,"p95":114515.0},"context.seed_text_fingerprints.parallel":{"max":0.0,"mean":0.0,"median":0.0,"min":0.0,"p95":0.0},"emit_base_changes":{"max":10110.636,"mean":10110.636,"median":10110.636,"min":10110.636,"p95":10110.636},"emit_derived_markers":{"max":8777.32,"mean":8777.32,"median":8777.32,"min":8777.32,"p95":8777.32},"prepare_context":{"max":265847.346,"mean":265847.346,"median":265847.346,"min":265847.346,"p95":265847.346},"total":{"max":295944.008,"mean":295944.008,"median":295944.008,"min":295944.008,"p95":295944.008}}},"output_signature":{"base_change_count":159,"derived_marker_count":0},"samples":{"peak_mem_bytes":[6679693919],"time_ms":[309482.997]},"stable_output_signature":true,"summary":{"peak_mem_bytes":{"max":6679693919,"mean":6679693919,"median":6679693919,"min":6679693919,"p95":6679693919},"time_ms":{"max":309482.997,"mean":309482.997,"median":309482.997,"min":309482.997,"p95":309482.997}}}},"parse_ms":{"new_graph":43451.074,"old_graph":38549.709,"total":82000.783}},{"case":{"name":"basichouse_same_file","new_path":"/Users/imantsliepins/Personal/Athar/data/BasicHouse.ifc","old_path":"/Users/imantsliepins/Personal/Athar/data/BasicHouse.ifc"},"metrics":{"diff_graphs":{"engine_timings_ms":{"samples":{"emit_base_changes":[0.0],"emit_derived_markers":[0.0],"prepare_context":[0.0],"total":[0.0]},"summary":{"emit_base_changes":{"max":0.0,"mean":0.0,"median":0.0,"min":0.0,"p95":0.0},"emit_derived_markers":{"max":0.0,"mean":0.0,"median":0.0,"min":0.0,"p95":0.0},"prepare_context":{"max":0.0,"mean":0.0,"median":0.0,"min":0.0,"p95":0.0},"total":{"max":0.0,"mean":0.0,"median":0.0,"min":0.0,"p95":0.0}}},"output_signature":{"base_change_count":0,"derived_marker_count":0},"samples":{"peak_mem_bytes":[516626],"time_ms":[431.136]},"stable_output_signature":true,"summary":{"peak_mem_bytes":{"max":516626,"mean":516626,"median":516626,"min":516626,"p95":516626},"time_ms":{"max":431.136,"mean":431.136,"median":431.136,"min":431.136,"p95":431.136}}}},"parse_ms":{"new_graph":0.0,"old_graph":40290.696,"total":40290.696}},{"case":{"name":"advancedproject_same_file","new_path":"/Users/imantsliepins/Personal/Athar/data/AdvancedProject.ifc","old_path":"/Users/imantsliepins/Personal/Athar/data/AdvancedProject.ifc"},"metrics":{"diff_graphs":{"engine_timings_ms":{"samples":{"emit_base_changes":[0.0],"emit_derived_markers":[0.0],"prepare_context":[0.0],"total":[0.0]},"summary":{"emit_base_changes":{"max":0.0,"mean":0.0,"median":0.0,"min":0.0,"p95":0.0},"emit_derived_markers":{"max":0.0,"mean":0.0,"median":0.0,"min":0.0,"p95":0.0},"prepare_context":{"max":0.0,"mean":0.0,"median":0.0,"min":0.0,"p95":0.0},"total":{"max":0.0,"mean":0.0,"median":0.0,"min":0.0,"p95":0.0}}},"output_signature":{"base_change_count":0,"derived_marker_count":0},"samples":{"peak_mem_bytes":[8008866],"time_ms":[509.158]},"stable_output_signature":true,"summary":{"peak_mem_bytes":{"max":8008866,"mean":8008866,"median":8008866,"min":8008866,"p95":8008866},"time_ms":{"max":509.158,"mean":509.158,"median":509.158,"min":509.158,"p95":509.158}}}},"parse_ms":{"new_graph":0.0,"old_graph":30991.764,"total":30991.764}}],"run_summary":{"total_cases":4,"total_elapsed_ms":874331.094,"total_elapsed_text":"14m 34s 331.1ms"}}
